tagmania/__init__.py
tagmania/delete_snapshots.py
tagmania/delete_volumes.py
tagmania/iac_tools/__init__.py
tagmania/iac_tools/clusterset.py
tagmania/iac_tools/filterset.py
tagmania/iac_tools/tagset.py
tagmania/iac_tools/util.py
tagmania/snapshot_manager.py
tagmania/start_cluster.py
tagmania/stop_cluster.py
tagmania/tag_manager.py
tagmania-2.5.1.dist-info/LICENSE
tagmania-2.5.1.dist-info/METADATA
tagmania-2.5.1.dist-info/WHEEL
tagmania-2.5.1.dist-info/entry_points.txt
tagmania-2.5.1.dist-info/RECORD
