Metadata-Version: 2.3
Name: tagmania
Version: 2.5.1
Summary: Manic tools for manipulating sets of tagged resources in AWS.
License: MIT License
Author: Samuel Vange
Author-email: 7166607+svange@users.noreply.github.com
Requires-Python: >=3.9,<4.0
Classifier: License :: Other/Proprietary License
Classifier: Programming Language :: Python :: 3
Classifier: Programming Language :: Python :: 3.9
Classifier: Programming Language :: Python :: 3.10
Classifier: Programming Language :: Python :: 3.11
Classifier: Programming Language :: Python :: 3.12
Classifier: Programming Language :: Python :: 3.13
Requires-Dist: boto3 (>=1.39.0,<2.0.0)
